sunnyportal/__init__.py
sunnyportal/client.py
sunnyportal/pandasclient.py
sunnyportal/requests.py
sunnyportal/responses.py
sunnyportal_py-0.0.4.dist-info/LICENSE.txt
sunnyportal_py-0.0.4.dist-info/METADATA
sunnyportal_py-0.0.4.dist-info/WHEEL
sunnyportal_py-0.0.4.dist-info/top_level.txt
sunnyportal_py-0.0.4.dist-info/RECORD
