Metadata-Version: 2.1
Name: sunnyportal-py
Version: 0.0.4
Summary: A Python client for SMA sunny portal
Home-page: https://github.com/EnergieID/sunnyportal-py
Author: Erik Johansson, EnergieID.be
Author-email: jan@energieid.be
License: GNU
Keywords: sma sunny portal solar pv python client api
Platform: UNKNOWN
Classifier: Development Status :: 3 - Alpha
Classifier: Intended Audience :: Developers
Classifier: Topic :: Scientific/Engineering
Classifier: License :: OSI Approved :: MIT License
Classifier: Programming Language :: Python :: 3.5
Classifier: Programming Language :: Python :: 3.6
Classifier: Programming Language :: Python :: 3.7
Requires-Dist: pandas
Requires-Dist: certifi
